colorspacious/__init__.py
colorspacious/basics.py
colorspacious/ciecam02.py
colorspacious/comparison.py
colorspacious/conversion.py
colorspacious/cvd.py
colorspacious/gold_values.py
colorspacious/illuminants.py
colorspacious/luoetal2006.py
colorspacious/testing.py
colorspacious/transform_graph.py
colorspacious/util.py
colorspacious/version.py
colorspacious-1.1.1.dist-info/DESCRIPTION.rst
colorspacious-1.1.1.dist-info/METADATA
colorspacious-1.1.1.dist-info/RECORD
colorspacious-1.1.1.dist-info/WHEEL
colorspacious-1.1.1.dist-info/metadata.json
colorspacious-1.1.1.dist-info/top_level.txt
