Metadata-Version: 2.0
Name: colorspacious
Version: 1.1.1
Summary: A powerful, accurate, and easy-to-use Python library for doing colorspace conversions
Home-page: https://github.com/njsmith/colorspacious
Author: Nathaniel J. Smith
Author-email: njs@pobox.com
License: MIT
Platform: UNKNOWN
Classifier: Development Status :: 4 - Beta
Classifier: Intended Audience :: Developers
Classifier: Intended Audience :: Science/Research
Classifier: License :: OSI Approved :: MIT License
Classifier: Programming Language :: Python :: 2
Classifier: Programming Language :: Python :: 3
Requires-Dist: numpy
